evocloud_sdk/__init__.py
evocloud_sdk/client.py
evocloud_sdk/common/__init__.py
evocloud_sdk/common/client.py
evocloud_sdk/common/exceptions.py
evocloud_sdk/common/signature.py
evocloud_sdk/common/utils.py
evocloud_sdk/linkpay/__init__.py
evocloud_sdk/linkpay/client.py
evocloud_sdk/linkpay/model.py
evocloud_sdk/linkpay/webhook.py
evocloud_sdk/merchant/__init__.py
evocloud_sdk/merchant/client.py
evocloud_sdk/merchant/model.py
evocloud_sdk-0.1.1.dist-info/METADATA
evocloud_sdk-0.1.1.dist-info/WHEEL
evocloud_sdk-0.1.1.dist-info/top_level.txt
evocloud_sdk-0.1.1.dist-info/RECORD
