Metadata-Version: 2.4
Name: evocloud-sdk
Version: 0.1.1
Summary: EVO Cloud Python SDK - 官方 Python 开发工具包，支持 LinkPay、Merchant 等多种支付方式
Author-email: EVO Cloud Team <support@everonet.com>
License: MIT
Project-URL: Homepage, https://github.com/everonet/evocloud-sdk-python
Project-URL: Documentation, https://docs.everonet.com/sdk/python
Project-URL: Repository, https://github.com/everonet/evocloud-sdk-python.git
Project-URL: Issues, https://github.com/everonet/evocloud-sdk-python/issues
Keywords: evocloud,payment,sdk,linkpay,merchant,alipay,wechat,visa,unionpay,e-commerce,fintech
Classifier: Development Status :: 4 - Beta
Classifier: Intended Audience :: Developers
Classifier: Topic :: Software Development :: Libraries :: Python Modules
Classifier: Topic :: Office/Business :: Financial :: Point-Of-Sale
Classifier: License :: OSI Approved :: MIT License
Classifier: Programming Language :: Python :: 3
Classifier: Programming Language :: Python :: 3.8
Classifier: Programming Language :: Python :: 3.9
Classifier: Programming Language :: Python :: 3.10
Classifier: Programming Language :: Python :: 3.11
Classifier: Programming Language :: Python :: 3.12
Classifier: Operating System :: OS Independent
Requires-Python: >=3.8
Requires-Dist: requests>=2.25.0
Requires-Dist: urllib3>=1.26.0
Provides-Extra: dev
Requires-Dist: pytest>=6.0; extra == "dev"
Requires-Dist: pytest-cov>=2.0; extra == "dev"
Requires-Dist: black>=21.0; extra == "dev"
Requires-Dist: flake8>=3.8; extra == "dev"
Requires-Dist: mypy>=0.800; extra == "dev"
Requires-Dist: pre-commit>=2.0; extra == "dev"
Provides-Extra: docs
Requires-Dist: sphinx>=4.0; extra == "docs"
Requires-Dist: sphinx-rtd-theme>=1.0; extra == "docs"
Requires-Dist: myst-parser>=0.15; extra == "docs"
Provides-Extra: test
Requires-Dist: pytest>=6.0; extra == "test"
Requires-Dist: pytest-cov>=2.0; extra == "test"
Requires-Dist: pytest-mock>=3.0; extra == "test"
Requires-Dist: responses>=0.18.0; extra == "test"
